rasterizer/__init__.py
rasterizer/lines.py
rasterizer/numba_impl.py
rasterizer/polygons.py
rasterizer/rasterizer.py
rasterizer-0.2.1.dist-info/METADATA
rasterizer-0.2.1.dist-info/WHEEL
rasterizer-0.2.1.dist-info/top_level.txt
rasterizer-0.2.1.dist-info/RECORD
