Metadata-Version: 2.4
Name: rasterizer
Version: 0.2.1
Summary: A Python package to rasterize GeoDataFrames
Author: Cyril Joly
Project-URL: Homepage, https://github.com/CyrilJl/rasterizer
Project-URL: Documentation, https://rasterizer.readthedocs.io
Requires-Python: >=3.10
Requires-Dist: geopandas
Requires-Dist: xarray
Requires-Dist: numpy
Requires-Dist: shapely
Requires-Dist: rioxarray
Requires-Dist: numba
Provides-Extra: test
Requires-Dist: pytest; extra == "test"
Requires-Dist: scipy; extra == "test"
